blockcypher/__init__.py
blockcypher/api.py
blockcypher/constants.py
blockcypher/crypto.py
blockcypher/utils.py
blockcypher-1.0.93.dist-info/LICENSE
blockcypher-1.0.93.dist-info/METADATA
blockcypher-1.0.93.dist-info/WHEEL
blockcypher-1.0.93.dist-info/top_level.txt
blockcypher-1.0.93.dist-info/RECORD
