Metadata-Version: 2.1
Name: blockcypher
Version: 1.0.93
Summary: BlockCypher Python Library
Home-page: https://github.com/blockcypher/blockcypher-python/
Author: Michael Flaxman
Author-email: mflaxman+blockcypher@gmail.com
License: UNKNOWN
Platform: UNKNOWN
License-File: LICENSE
